{"is_source_file": true, "format": "JavaScript (React JSX)", "description": "Main frontend application component for a notes manager app, defining layout, theme toggling, note list rendering, and import/export functionality.", "external_files": ["./store/useNotesStore", "./utils/theme", "./components/Layout/TopNav", "./components/Layout/Sidebar", "./App.css"], "external_methods": ["useNotesStore", "applyTheme", "getSystemPreferredTheme"], "published": ["App"], "classes": [], "methods": [{"name": "App()", "description": "Root React component that sets up theme, layout, and wraps child components.", "scope": "", "scopeKind": ""}, {"name": "StoreActionBridge({ onNewNote })", "description": "A helper component to expose store actions to global scope for the TopNav component.", "scope": "", "scopeKind": ""}, {"name": "MainView()", "description": "Main view component that displays list of notes with filtering, sorting, import/export, and note actions.", "scope": "", "scopeKind": ""}], "calls": ["React.useEffect", "React.useState", "applyTheme", "getSystemPreferredTheme", "useNotesStore", "window.__notesCreateNew", "actions.createNote", "actions.importNotes", "actions.selectNote", "actions.togglePin", "actions.toggleArchive", "actions.deleteNote"], "search-terms": ["React layout", "Theme toggling", "Notes list rendering", "Import export notes", "Bridge pattern for store actions"], "state": 2, "file_id": 7, "knowledge_revision": 41, "git_revision": "33fbd0833094b1db963040c2638e7629eb03d024", "revision_history": [{"25": "e4984a014603288a476740f942b4fddf4370b79f"}, {"34": "e4984a014603288a476740f942b4fddf4370b79f"}, {"41": "33fbd0833094b1db963040c2638e7629eb03d024"}], "ctags": [{"_type": "tag", "name": "App", "path": "/home/kavia/workspace/code-generation/simple-notes-manager-35161-35170/notes_frontend/src/App.js", "pattern": "/^function App() {$/", "language": "JavaScript", "kind": "function", "signature": "()"}, {"_type": "tag", "name": "MainView", "path": "/home/kavia/workspace/code-generation/simple-notes-manager-35161-35170/notes_frontend/src/App.js", "pattern": "/^function MainView() {$/", "language": "JavaScript", "kind": "function", "signature": "()"}, {"_type": "tag", "name": "StoreActionBridge", "path": "/home/kavia/workspace/code-generation/simple-notes-manager-35161-35170/notes_frontend/src/App.js", "pattern": "/^function StoreActionBridge({ onNewNote }) {$/", "language": "JavaScript", "kind": "function", "signature": "({ onNewNote })"}, {"_type": "tag", "name": "file", "path": "/home/kavia/workspace/code-generation/simple-notes-manager-35161-35170/notes_frontend/src/App.js", "pattern": "/^                const file = e.target.files?.[0];$/", "language": "JavaScript", "kind": "constant", "scope": "onChange", "scopeKind": "class"}, {"_type": "tag", "name": "json", "path": "/home/kavia/workspace/code-generation/simple-notes-manager-35161-35170/notes_frontend/src/App.js", "pattern": "/^                  const json = JSON.parse(text);$/", "language": "JavaScript", "kind": "constant", "scope": "onChange", "scopeKind": "class"}, {"_type": "tag", "name": "text", "path": "/home/kavia/workspace/code-generation/simple-notes-manager-35161-35170/notes_frontend/src/App.js", "pattern": "/^                const text = await file.text();$/", "language": "JavaScript", "kind": "constant", "scope": "onChange", "scopeKind": "class"}, {"_type": "tag", "name": "theme", "path": "/home/kavia/workspace/code-generation/simple-notes-manager-35161-35170/notes_frontend/src/App.js", "pattern": "/^          theme={theme}$/", "language": "JavaScript", "kind": "field", "scope": "App.theme", "scopeKind": "class"}, {"_type": "tag", "name": "toggleTheme", "path": "/home/kavia/workspace/code-generation/simple-notes-manager-35161-35170/notes_frontend/src/App.js", "pattern": "/^          onToggleTheme={toggleTheme}$/", "language": "JavaScript", "kind": "field", "scope": "App.onToggleTheme", "scopeKind": "class"}], "hash": "6ff271781ca23d55602640bc43ac4560", "format-version": 4, "code-base-name": "notes_frontend", "filename": "notes_frontend/src/App.js", "fields": [{"name": "theme={theme}", "scope": "App.theme", "scopeKind": "class", "description": "unavailable"}, {"name": "onToggleTheme={toggleTheme}", "scope": "App.onToggleTheme", "scopeKind": "class", "description": "unavailable"}]}