{"is_source_file": false, "format": "", "description": "", "external_files": [], "external_methods": [], "published": [], "classes": [], "methods": [], "calls": [], "search-terms": [], "state": 2, "file_id": 10, "knowledge_revision": 43, "git_revision": "33fbd0833094b1db963040c2638e7629eb03d024", "hash": "60522e92f2aa902f38ba3b92e786b69c", "format-version": 4, "code-base-name": "notes_frontend", "filename": "notes_frontend/src/index.css", "revision_history": [{"43": "33fbd0833094b1db963040c2638e7629eb03d024"}]}